plot_helper/__init__.py
plot_helper-0.1.2.dist-info/LICENSE
plot_helper-0.1.2.dist-info/WHEEL
plot_helper-0.1.2.dist-info/METADATA
plot_helper-0.1.2.dist-info/RECORD
